llama_index/postprocessor/siliconflow_rerank/__init__.py
llama_index/postprocessor/siliconflow_rerank/base.py
llama_index_postprocessor_siliconflow_rerank-0.3.1.dist-info/METADATA
llama_index_postprocessor_siliconflow_rerank-0.3.1.dist-info/WHEEL
llama_index_postprocessor_siliconflow_rerank-0.3.1.dist-info/licenses/LICENSE
llama_index_postprocessor_siliconflow_rerank-0.3.1.dist-info/RECORD
