Metadata-Version: 2.4
Name: llama-index-postprocessor-siliconflow-rerank
Version: 0.3.1
Summary: llama-index postprocessor siliconflow rerank integration
Author: nightosong
License-Expression: MIT
License-File: LICENSE
Requires-Python: <4.0,>=3.9
Requires-Dist: llama-index-core<0.15,>=0.13.0
